README.rst
setup.py
djangosqlash/__init__.py
djangosqlash/testing.py
djangosqlash.egg-info/PKG-INFO
djangosqlash.egg-info/SOURCES.txt
djangosqlash.egg-info/dependency_links.txt
djangosqlash.egg-info/entry_points.txt
djangosqlash.egg-info/not-zip-safe
djangosqlash.egg-info/requires.txt
djangosqlash.egg-info/top_level.txt
djangosqlash/tests/__init__.py
djangosqlash/tests/settings.py
djangosqlash/tests/test_it.py